{
  "id": "shikibetsu",
  "title": "紛らわしい語の識別",
  "category": "識別",
  "layer": 2,
  "summary": "同表記の語を見分ける古文最頻出の識別問題。「なむ」「に」「ぬ」が最重要。",
  "sections": [
    {
      "heading": "最重要 3 語の判別",
      "content": "### なむ（4 通り）\n| 候補 | 接続 | 意味 |\n|:--|:--|:--|\n| 係助詞 | 文中（係り結び） | 強調（訳出不要） |\n| 終助詞 | **未然形**＋なむ（文末） | 他者への願望「〜てほしい」 |\n| 助動詞「ぬ＋む」 | **連用形**＋なむ | 強意＋推量「きっと〜だろう」 |\n| ナ変未然形＋む | 「死な・往な」＋む | 推量（「死なむ」等） |\n\n### に（5 通り）\n| 候補 | 判別法 | 訳 |\n|:--|:--|:--|\n| 完了「ぬ」の連用形 | 直後に「き・けり・たり」 | 〜てしまって |\n| 断定「なり」の連用形 | **「であって」と訳せる** | 〜であって |\n| 格助詞 | 体言の後、場所・時・対象 | 〜に |\n| 接続助詞 | 連体形の後、文の接続 | 〜ので／〜のに |\n| 形容動詞の連用形 | 「だ」に置換可能 | 〜に |\n\n### ぬ（3 通り）\n| 候補 | 接続 | 意味 |\n|:--|:--|:--|\n| 打消「ず」の連体形 | **未然形**＋ぬ | 〜ない |\n| 完了「ぬ」の終止形 | **連用形**＋ぬ | 〜てしまった |\n| ナ変動詞の終止形 | 語幹＋ぬ | 死ぬ／往ぬ |\n\n> **核心**: 直前の活用形で決まる。未然形→打消、連用形→完了。",
      "priority": "essential"
    },
    {
      "heading": "助詞系の識別（が・して・と・とも）",
      "content": "### が\n| 候補 | 接続 | 意味 |\n|:--|:--|:--|\n| 格助詞 | 体言・連体形＋が | 連体修飾「〜の」／主格「〜が」 |\n| 接続助詞 | 連体形＋が | 逆接「〜けれども」／単純接続 |\n\n**判別**: 直後に用言が来て文が続くなら接続助詞。\n\n### して\n| 候補 | 接続 | 意味 |\n|:--|:--|:--|\n| 格助詞 | **体言**＋して | 手段・使役の対象 |\n| サ変「す」連用形＋接続助詞「て」 | 語幹＋して | 動詞活用 |\n\n### と / とも\n- **と**: 格助詞（並列・引用）／接続助詞（順接仮定）\n- **とも**: 接続助詞「〜としても」\n\n判別は文脈と接続先の活用形で。",
      "priority": "important"
    },
    {
      "heading": "活用語尾系の識別（けれ・し・しか・せ）",
      "content": "### けれ\n| 候補 | 接続 |\n|:--|:--|\n| 助動詞「けり」の已然形 | **連用形**＋けれ |\n| 形容詞ク／シク活用の已然形 | 語幹＋けれ |\n\n### し\n| 候補 | 接続 |\n|:--|:--|\n| 助動詞「き」の連体形 | **連用形**＋し |\n| 形容詞ク／シク活用の終止形 | 語幹＋し |\n\n### しか\n| 候補 | 形 |\n|:--|:--|\n| 助動詞「き」の已然形 | 連用形＋しか |\n| 助動詞「まし」の未然形 | 未然形＋ましか（反実仮想の条件部） |\n\n> **「ましかば…まし」なら「まし」の未然形。**\n\n### せ（最頻出）\n| 候補 | 形 |\n|:--|:--|\n| 過去「き」の未然形 | 「せば…まし」構文専用 |\n| 使役「す」の未然／連用形 | 未然形＋せ |\n| サ変「す」の未然／已然／命令形 | 単独 |\n\n> **「せば…まし」の「せ」は過去「き」の未然形**（頻出）。",
      "priority": "important"
    },
    {
      "heading": "助動詞系の識別（なり・たり・る・れ）",
      "content": "### なり（詳細は [断定](./jodoshi-dantei)）\n| 候補 | 接続 |\n|:--|:--|\n| 断定「なり」 | **体言・連体形** |\n| 伝聞推定「なり」 | **終止形** |\n| 形容動詞ナリ活用 | 語幹 |\n\nラ変後: **あるなり＝断定／あんなり＝伝聞推定**（撥音便化が決め手）。\n\n### たり\n| 候補 | 接続 |\n|:--|:--|\n| 完了・存続 | **連用形**＋たり |\n| 断定 | **体言**＋たり |\n| 形容動詞タリ活用 | 漢語語幹＋たり |\n\n### る／れ\n| 候補 | 接続 |\n|:--|:--|\n| 受身・可能・自発・尊敬「る」 | 四段・ナ変・ラ変の**未然形** |\n| 自発「らる」（活用の一部が「れ」） | 上記以外の未然形 |\n| 完了「り」の一部 | サ変未然形・四段已然形＋り |\n\n→ 詳細は [受身・使役・尊敬](./jodoshi-ukemi-shieki-sonkei) 参照。",
      "priority": "important"
    },
    {
      "heading": "判別のベストプラクティス",
      "content": "1. **直前の活用形を先に特定**: 未然形・連用形・連体形・已然形のいずれかで候補が大きく絞れる\n2. **訳で確認**: 複数候補が残ったら各候補の訳を当てて、文意が通るものを採用\n3. **文末か文中か**: 係り結び／終助詞は文末、格助詞・接続助詞は文中\n4. **ラ変の後は撥音便チェック**: 「あん〜」「あ〜」は伝聞推定のサイン\n5. **対比で覚える**: 「せば…まし」「ましかば…まし」のように、構文単位で判別できる形を覚える\n\n> 識別問題は**古文入試の最頻出テーマ**。典型構文を丸ごと覚えるのが最短ルート。",
      "priority": "essential"
    }
  ],
  "textExamples": [],
  "keyPoints": [
    "最重要 3 語: なむ（4 通り）・に（5 通り）・ぬ（3 通り）",
    "直前の活用形が判別の第一手がかり",
    "ラ変後の撥音便: 「あんなり」→伝聞推定",
    "「せば…まし」「ましかば…まし」は構文で丸覚え",
    "「に」→「であって」で訳せるなら断定「なり」の連用形"
  ],
  "studySteps": [
    "「な むに ぬ」の判別フロー（未然形／連用形／体言）を暗記",
    "「に」の 5 候補と判別順序を覚える",
    "ラ変後の撥音便（あんなり）に反応できるようにする",
    "「せば…まし」構文を音と共に覚える",
    "過去問で識別問題を 10 題解いて定着させる"
  ]
}
