{
  "textId": "cec7f3b46f",
  "annotations": [
    {
      "sentenceId": "s1",
      "guide": "物語冒頭の一文。「いづれの御時にか」は時代不特定の書き出し。「が」は同格の格助詞で、主語が隠れている構造を見抜く。",
      "hints": [
        {
          "type": "structure",
          "label": "「いづれの御時にか」の機能",
          "points": [
            "「か」は疑問の係助詞 → 本来なら連体形で結ぶが結び省略",
            "「どの帝の御代であったか（知らないが）」と時代をぼかす書き出し",
            "物語世界の虚構性を示す定型句（『竹取物語』「いまは昔」と同様の機能）"
          ]
        },
        {
          "type": "grammar",
          "label": "「が」は同格",
          "points": [
            "「きはにはあらぬが、すぐれて時めきたまふ」の「が」＝同格（〜で、しかも）",
            "「あらぬ」は連体形 → 下に「人・方」などの体言が省略されている",
            "「身分の高くない方で、（しかもその方が）抜群に寵愛を受けていらっしゃる方」と訳す"
          ]
        },
        {
          "type": "subject",
          "label": "主語は桐壺更衣",
          "points": [
            "「さぶらひたまひける」＝謙譲＋尊敬 → 女御・更衣が帝に仕える構図",
            "「時めきたまふ」の主語は名前の出ない「ある方」＝後の桐壺更衣",
            "物語は主人公の名を伏せたまま始まる — これが読者を引き込む仕掛け"
          ]
        },
        {
          "type": "vocab",
          "label": "「やむごとなし」「時めく」",
          "points": [
            "「やむごとなし」＝高貴だ・格別だ（現代語「やむを得ない」とは別系統）",
            "「きは」＝身分・家柄",
            "「時めく」＝その時々の寵愛を受けて栄える（帝の寵愛を受ける意）"
          ]
        }
      ]
    },
    {
      "sentenceId": "s2",
      "guide": "主語は周囲の女御たち。「われは（と）」は心内の自負を引用する表現。「たまふ」単独敬語は貴人一般に用いる。",
      "hints": [
        {
          "type": "subject",
          "label": "主語は「御方々」＝女御たち",
          "points": [
            "「思ひあがりたまへる御方々」が主語 — 文末近くまで読まないと判明しない",
            "この「御方々」は前文の「時めきたまふ」方（＝桐壺更衣）とは別人",
            "「おとしめ嫉みたまふ」の動作主も同じ女御たち"
          ]
        },
        {
          "type": "structure",
          "label": "「われはと思ひあがり」の構造",
          "points": [
            "「われは」＝「自分こそは（第一の寵愛を受けるべきだ）」という心内語",
            "「と」で引用 → 自負の内容を直接引用する形",
            "省略を補う：「われは（時めくべき人なれ）と」"
          ]
        },
        {
          "type": "vocab",
          "label": "「めざまし」の古語義",
          "points": [
            "「めざまし」＝目ざわりだ・不愉快だ（現代語「目覚ましい」と真逆）",
            "身分の低い者が優遇されることへの憤懣を表す語",
            "「おとしむ」＝見下す、「嫉む」＝ねたむ"
          ]
        }
      ]
    },
    {
      "sentenceId": "s3",
      "guide": "同じ身分や下の更衣たち＝嫉妬の主体の転換。「まして」は前文からの程度の上昇を示す。",
      "hints": [
        {
          "type": "subject",
          "label": "主語は下位の更衣たち",
          "points": [
            "s2は「女御」（上位）、s3は「更衣」（下位）— 嫉妬者の階層が下りていく",
            "「下﨟の更衣たち」＝桐壺更衣より地位の低い更衣たち",
            "敬語「たまふ」が付かない → 身分の低さを文法が示している"
          ]
        },
        {
          "type": "method",
          "label": "「まして」で程度比較",
          "points": [
            "「まして」＝なおさら・いっそう（前文を受けて程度が上がる）",
            "s2の女御（同格・格上）の嫉みすらひどいのに、下位の更衣はそれ以上、の論理",
            "敬語の有無で人物階層を読み取る典型例"
          ]
        },
        {
          "type": "vocab",
          "label": "「やすからず」",
          "points": [
            "「やすし」＝心穏やか・安らかである",
            "「やすからず」＝心穏やかでない・気がおさまらない",
            "嫉妬心の表出を婉曲に述べる古文の常套表現"
          ]
        }
      ]
    },
    {
      "sentenceId": "s4",
      "guide": "長文。前半「つもりにやありけむ」で疑問の挿入句、後半「憚らせたまはず」で二重尊敬＝主語は帝。主語の転換を敬語で追跡する。",
      "hints": [
        {
          "type": "subject",
          "label": "主語は更衣 → 帝へ転換",
          "points": [
            "前半「いとあつしくなりゆき」「里がちなる」の主語は更衣（病弱化・里下がり）",
            "後半「思ほして」「憚らせたまはず」の主語は帝（二重尊敬が合図）",
            "「〜を、〜思ほして」の「を」で主語が更衣→帝に切り替わる"
          ]
        },
        {
          "type": "grammar",
          "label": "二重尊敬「せたまふ」は帝専用",
          "points": [
            "「憚らせたまはず」の「せ」＝尊敬の助動詞「す」連用形、「たまは」＝尊敬補助動詞",
            "尊敬＋尊敬 ＝ 二重尊敬（最高敬語）→ 主語は帝に限定される",
            "「え〜ず」＝不可能（〜できない）→ 帝でさえ世間の非難を気にせずにいられない"
          ]
        },
        {
          "type": "grammar",
          "label": "「にやありけむ」疑問の挿入",
          "points": [
            "「つもりにやありけむ」の「や」＝疑問の係助詞、「けむ」＝過去推量",
            "語り手の推測「〜のせいだったのだろうか」を挿入する",
            "文全体の主述を中断させる構造 — 前後で主語が変わる合図"
          ]
        },
        {
          "type": "vocab",
          "label": "「あつし」「ためし」",
          "points": [
            "「あつし」＝病気がちだ（「篤し」。現代語の「熱い」ではない）",
            "「里がち」＝実家に下がりがち（病気治療のため）",
            "「ためし」＝先例・語り草"
          ]
        }
      ]
    },
    {
      "sentenceId": "s5",
      "guide": "主語は宮中の男性貴族たち。「あいなく」は彼らの困惑を示す。「人の御おぼえ」で更衣への寵愛の話題に戻す。",
      "hints": [
        {
          "type": "subject",
          "label": "主語は上達部・上人",
          "points": [
            "文頭「上達部・上人なども」と主語が明示されている",
            "「目をそばめつつ」＝目をそむけながら — 見ていられないという態度",
            "「人の御おぼえなり」の「人」は更衣を指す（視点の焦点が更衣に戻る）"
          ]
        },
        {
          "type": "vocab",
          "label": "「あいなし」「まばゆし」「おぼえ」",
          "points": [
            "「あいなし」＝わけもなく・おせっかいにも（古語義）",
            "「まばゆし」＝まぶしい・正視できない（過度の寵愛が眩しい）",
            "「おぼえ」＝世間の評判・信望、（人からの）寵愛"
          ]
        },
        {
          "type": "method",
          "label": "周囲の視線を描く一文",
          "points": [
            "女御 → 更衣 → 上達部と、嫉妬と困惑の輪が宮中全体に広がる構図",
            "「目をそばめ」という身体描写で宮廷の雰囲気を伝える",
            "この一文が次の「唐土にも」の比較（中国の先例への飛躍）への布石"
          ]
        }
      ]
    },
    {
      "sentenceId": "s6",
      "guide": "きわめて長い一文。「こそ〜けれ」の係り結び（引用内）、接続助詞「に」で主語転換。最後の「まじらひたまふ」の主語は更衣。",
      "hints": [
        {
          "type": "subject",
          "label": "複数の主語が入れ替わる",
          "points": [
            "「唐土にも〜悪しかりけれ」＝世間の噂の内容（特定の主語なし、一般論）",
            "「天の下にも〜なりゆく」＝「世の中」が主語",
            "「まじらひたまふ」の主語は更衣（「たまふ」が付くので貴人＝更衣）"
          ]
        },
        {
          "type": "grammar",
          "label": "「こそ〜けれ」係り結び",
          "points": [
            "「事の起こりにこそ〜悪しかりけれ」の「こそ」＝強意の係助詞",
            "結びは已然形「けれ」（過去「けり」の已然形）",
            "引用「と」の内側での係り結び — 世間の噂を強調する表現"
          ]
        },
        {
          "type": "structure",
          "label": "楊貴妃故事の引用",
          "points": [
            "「唐土にも」以下は白居易「長恨歌」（楊貴妃と玄宗）を踏まえる",
            "「かかる事の起こりにこそ」＝こうしたこと（偏愛）こそが原因で",
            "世が乱れた唐の先例を引くことで、帝の偏愛の危険性を暗示する"
          ]
        },
        {
          "type": "vocab",
          "label": "「はしたなし」「かたじけなし」",
          "points": [
            "「はしたなし」＝いたたまれない・中途半端で気まずい",
            "「かたじけなし」＝恐れ多い・もったいない",
            "「たぐひなし」＝比類がない — 帝の情愛の格別さを表す"
          ]
        }
      ]
    },
    {
      "sentenceId": "s7",
      "guide": "更衣の家庭背景。「なむ〜けれ」の係り結び（結びの流れ）、「〜けれど」の逆接で「後見の欠如」という結論に導く。",
      "hints": [
        {
          "type": "subject",
          "label": "主語は母北の方",
          "points": [
            "「父の大納言は亡くなりて」で父の死を先置き",
            "「母北の方なむ」＝「母上こそが」— 「なむ」で母を強調提示",
            "「もてなしたまひけれど」の動作主は母北の方（「たまふ」付き）"
          ]
        },
        {
          "type": "grammar",
          "label": "「なむ〜けれ」の係り結びの流れ",
          "points": [
            "「なむ」は本来連体形「ける」で結ぶが、ここは「けれど」と逆接で続く",
            "これを「結びの流れ（消滅）」という — 接続助詞で文が続くと係り結びが消える",
            "識別ポイント：「なむ」「ぞ」「や」「か」の後に接続助詞が来ると結びが流れる"
          ]
        },
        {
          "type": "structure",
          "label": "「けれど〜なければ〜心細げなり」",
          "points": [
            "「けれど」で譲歩（母は立派にふるまうが）",
            "「後見しなければ」で原因（後ろ盾がない）",
            "最終的に「心細げなり」— 家柄の弱さが更衣の立場を支えきれないという論理"
          ]
        },
        {
          "type": "vocab",
          "label": "「よし」「後見」",
          "points": [
            "「よし」＝由緒・教養（「いにしへの人のよしある」＝古風で教養のある人）",
            "「後見（うしろみ）」＝後ろ盾・世話役（政治的な支援者）",
            "「はかばかし」＝しっかりしている・頼りになる"
          ]
        }
      ]
    },
    {
      "sentenceId": "s8",
      "guide": "皇子誕生の場面。「や〜けむ」の疑問の係り結び。「さへ」は添加の副助詞で、寵愛に加えて皇子まで得たことを示す。",
      "hints": [
        {
          "type": "subject",
          "label": "主語は皇子（若宮）",
          "points": [
            "「玉の男皇子さへ生まれたまひぬ」— 主語は生まれた皇子",
            "「たまひ」＝尊敬補助動詞 → 皇子への敬意",
            "帝と更衣の子（後の光源氏）の誕生を告げる物語の転換点"
          ]
        },
        {
          "type": "grammar",
          "label": "「や〜けむ」疑問の係り結び",
          "points": [
            "「御契りや深かりけむ」の「や」＝疑問の係助詞",
            "結びは連体形「けむ」（過去推量）",
            "「前世の宿縁が深かったのだろうか」と語り手が推測を挿入"
          ]
        },
        {
          "type": "vocab",
          "label": "「さへ」の識別",
          "points": [
            "「さへ」＝添加の副助詞「〜までも」（すでに何かがある上にさらに）",
            "「だに」＝最小限（〜だけでも）とは区別すること",
            "ここでは「寵愛に加えて皇子までも」のニュアンス"
          ]
        },
        {
          "type": "method",
          "label": "「きよらなり」の格の違い",
          "points": [
            "「きよらなり」＝光り輝くほど美しい（最上級の美）",
            "「きよげなり」＝こざっぱりと美しい（一ランク下）",
            "若宮に「きよらなり」が使われるのは特別な美しさを示す"
          ]
        }
      ]
    },
    {
      "sentenceId": "s9",
      "guide": "「心もとながらせたまひて」の二重尊敬で主語は帝。「参らせて」は使役＋謙譲。「御覧ず」は帝の専用語。",
      "hints": [
        {
          "type": "subject",
          "label": "主語は帝",
          "points": [
            "「心もとながらせたまひて」＝二重尊敬 → 主語は帝",
            "「御覧ずる」＝「見る」の尊敬（最高敬語）→ やはり帝",
            "若宮を実家から宮中へ呼び寄せて対面する場面"
          ]
        },
        {
          "type": "grammar",
          "label": "「せ」の識別：尊敬か使役か",
          "points": [
            "「心もとながらせたまひて」の「せ」＝尊敬（後に「たまふ」→ 二重尊敬）",
            "「参らせて」の「せ」＝使役（人に参上させて）",
            "見分け方：「せ＋たまふ」は尊敬、「せ（＋て／ず等）」で独立なら使役"
          ]
        },
        {
          "type": "vocab",
          "label": "「いつしか」「めづらかなり」",
          "points": [
            "「いつしか」＝早く・はやく（〜したい）— 待ちきれない気持ち",
            "「心もとなし」＝待ち遠しい・じれったい",
            "「めづらかなり」＝めったにない・尋常でない（若宮の容姿の並外れたさまを表す）"
          ]
        }
      ]
    },
    {
      "sentenceId": "s10",
      "guide": "第一皇子との対比。「きこゆ」は謙譲、「並びたまふ」は尊敬と、敬語の向きで人物関係を読む。最後の「限りなし」で帝の溺愛を強調。",
      "hints": [
        {
          "type": "subject",
          "label": "二人の皇子の対比構造",
          "points": [
            "「一の皇子」（右大臣の女御の子）と「この君」（若宮・光源氏）の対比",
            "「もてかしづききこゆれど」の主語は世間の人々（一の皇子を大切にする）",
            "「思ほしかしづきたまふ」の主語は帝（若宮をひそかに秘蔵する）"
          ]
        },
        {
          "type": "grammar",
          "label": "「きこゆ」と「たまふ」で敬意の向きを判定",
          "points": [
            "「もてかしづききこゆ」＝謙譲 → 一の皇子への敬意（世間が一の皇子を）",
            "「並びたまふべくもあらざりければ」＝尊敬＋可能の打消 → 若宮の美しさの絶対性",
            "「思ほしかしづきたまふ」＝尊敬（帝が動作主）＋尊敬（若宮への敬意）"
          ]
        },
        {
          "type": "structure",
          "label": "「〜ど／ば」で論理を追う",
          "points": [
            "「もてかしづききこゆれど」で逆接 — 世間は一の皇子を立てるが…",
            "「あらざりければ」で原因 — 比較にならないので",
            "「私物に思ほしかしづきたまふこと限りなし」が結論 — 帝の本心は若宮に傾く"
          ]
        },
        {
          "type": "vocab",
          "label": "「よせ」「まうけの君」「私物」",
          "points": [
            "「よせ」＝後ろ盾・信望（「よす」の名詞形）",
            "「まうけの君」＝皇太子・東宮",
            "「私物（わたくしもの）」＝私的に大切にするもの、秘蔵の子"
          ]
        }
      ]
    },
    {
      "sentenceId": "s11",
      "guide": "主語は更衣。「べき」の意味判別がポイント。「ざりき」の「き」は直接経験の過去で、語り手の視点を転じる。",
      "hints": [
        {
          "type": "subject",
          "label": "主語は更衣（冒頭の方）",
          "points": [
            "「上宮仕へしたまふ」に「たまふ」が付く → 貴人＝更衣",
            "主語表示はないが、文脈（桐壺更衣の話題）で判定する",
            "「初めより」で s2 と同じ書き出しを繰り返し、話題を更衣に戻す合図"
          ]
        },
        {
          "type": "grammar",
          "label": "「べき」＝当然",
          "points": [
            "「上宮仕へしたまふべき」の「べき」＝当然（〜はずの／〜べき）",
            "「おしなべての上宮仕へ」＝ふつうの女官のお勤め",
            "「そんな身分の低い勤めをする方ではなかった」と否定する流れ"
          ]
        },
        {
          "type": "vocab",
          "label": "「おしなべて」",
          "points": [
            "「おしなべて」＝ひととおり・一般に・ふつうに",
            "身分の低い仕え方を指して「並の」というニュアンス",
            "更衣はもともと格のある家柄であることを強調"
          ]
        }
      ]
    },
    {
      "sentenceId": "s12",
      "guide": "最長文。主語が帝と更衣の間で何度も入れ替わる。敬語を手掛かりに分節。最後に「一の皇子の女御」（弘徽殿女御）の疑念に帰着する。",
      "hints": [
        {
          "type": "subject",
          "label": "主語の追跡（長大な複合文）",
          "points": [
            "「おぼえ〜上衆めかしけれど」＝更衣の周囲の評判（主語は更衣）",
            "「まつはさせたまふ」「まう上らせたまふ」「もてなさせたまひし」＝二重尊敬 → 帝",
            "「この皇子生まれたまひて」の主語は若宮",
            "「おぼし疑へり」の主語は一の皇子の女御（弘徽殿女御）— 文末で明示"
          ]
        },
        {
          "type": "grammar",
          "label": "二重尊敬の連打で帝の行動を追う",
          "points": [
            "「まつはさせたまふ」「まう上らせたまふ」「さぶらはせたまひ」「もてなさせたまひし」",
            "すべて「せたまふ／させたまふ」＝最高敬語 → 動作主は帝",
            "帝が更衣を離さず側に置く様子が敬語の連続で描かれる"
          ]
        },
        {
          "type": "structure",
          "label": "「〜ほどに」で時間経過と転換",
          "points": [
            "「もてなさせたまひしほどに」＝そうしていらっしゃるうちに",
            "「ほどに」＝時間経過＋場面転換の合図",
            "ここで話題が「更衣の立場の軽さ」から「皇子誕生後の別格の処遇」へ転換"
          ]
        },
        {
          "type": "vocab",
          "label": "「坊」「ようせずは」「なめり」",
          "points": [
            "「坊」＝東宮（皇太子）の御所。転じて皇太子位を指す",
            "「ようせずは」＝悪くすると・下手をすると（仮定）",
            "「なめり」＝「なるめり」の撥音便「なんめり」から「ん」が脱落。推定「〜のようだ」"
          ]
        }
      ]
    },
    {
      "sentenceId": "s13",
      "guide": "一の皇子の女御（弘徽殿女御）の立場を説明。「ぞ〜ける」の係り結び。「思ひきこえさせたまひける」の複雑な敬語を分析する。",
      "hints": [
        {
          "type": "subject",
          "label": "主語は帝",
          "points": [
            "「思ひきこえさせたまひける」の主語は帝（最高敬語の塊）",
            "「参りたまひて」「おはしませば」の主語は弘徽殿女御",
            "帝が弘徽殿女御の諫言を煩わしく思う、という構図"
          ]
        },
        {
          "type": "grammar",
          "label": "三層の敬語「きこえさせたまふ」",
          "points": [
            "「きこえ」＝謙譲補助動詞（弘徽殿女御への敬意）",
            "「させ」＝尊敬の助動詞、「たまふ」＝尊敬補助動詞 → 二重尊敬で帝への敬意",
            "全体で「〜に対して申し上げなさる」— 主語は帝、敬意の対象は弘徽殿女御"
          ]
        },
        {
          "type": "grammar",
          "label": "「ぞ〜ける」係り結び",
          "points": [
            "「御いさめをのみぞ〜思ひきこえさせたまひける」の「ぞ」＝強意",
            "結びは連体形「ける」（過去の助動詞「けり」）",
            "「（弘徽殿女御の）諫めをばかりは」と強調する構文"
          ]
        },
        {
          "type": "vocab",
          "label": "「なべてならず」「いさめ」",
          "points": [
            "「なべてならず」＝並々でない・格別だ（「なべて」＝一般に）",
            "「いさめ」＝諫め・忠告",
            "「わづらはし」＝わずらわしい、「心苦し」＝気の毒だ・つらい"
          ]
        }
      ]
    },
    {
      "sentenceId": "s14",
      "guide": "主語は再び更衣へ。「きこえながら」の謙譲＋逆接で帝と更衣の関係を示す。「ぞ〜したまふ」の係り結びで閉じる。",
      "hints": [
        {
          "type": "subject",
          "label": "主語は更衣",
          "points": [
            "「頼みきこえながら」＝帝を頼み申し上げながら → 主語は頼む側の更衣",
            "「ものはかなきありさま」「もの思ひをぞしたまふ」も更衣",
            "「きこゆ」（謙譲）の向かう先が帝、主語が更衣という関係"
          ]
        },
        {
          "type": "grammar",
          "label": "「ぞ〜したまふ」係り結び",
          "points": [
            "「もの思ひをぞしたまふ」の「ぞ」＝強意の係助詞",
            "結びは連体形「したまふ」（サ変「す」連体形＋「たまふ」）",
            "「物思いばかりをなさる」と更衣の心労を強調"
          ]
        },
        {
          "type": "vocab",
          "label": "「かしこし」「なかなかなり」",
          "points": [
            "「かしこし」＝畏れ多い・恐ろしいほど立派だ（帝の庇護の尊さ）",
            "「おとしめ」＝軽んじる、「きずを求む」＝欠点を探す",
            "「なかなかなり」＝かえって・中途半端だ（寵愛ゆえの苦労の皮肉）"
          ]
        }
      ]
    },
    {
      "sentenceId": "s15",
      "guide": "わずか6文字の短文で部屋名「桐壺」を明示。この巻名の由来であり、「清涼殿から最遠」という物理的距離が次の苦難の伏線になる。",
      "hints": [
        {
          "type": "structure",
          "label": "短文の効果",
          "points": [
            "「御局は桐壺なり」— 断定で短く言い切る",
            "長文の連続の中にこの短文を置くことで強く印象づける",
            "「桐壺」が物語の第一帖の題名であり、更衣の通称となる"
          ]
        },
        {
          "type": "method",
          "label": "宮中の空間を押さえる",
          "points": [
            "桐壺（淑景舎）は清涼殿（帝の居所）から最も遠い殿舎",
            "帝のもとへ上るたびに長い廊下を通らねばならない → 次文以降の苦難の伏線",
            "身分の低い更衣に最遠の部屋が与えられた事実が、更衣の立場を空間的に示す"
          ]
        }
      ]
    },
    {
      "sentenceId": "s16",
      "guide": "主語は帝。「過ぎさせたまひて」の二重尊敬で帝の行動を描く。「人の御心を尽くしたまふ」の「人」は更衣でなく周囲。",
      "hints": [
        {
          "type": "subject",
          "label": "主語の判別",
          "points": [
            "「過ぎさせたまひて」＝二重尊敬 → 主語は帝（他の女御の部屋前を素通り）",
            "「人の御心を尽くしたまふ」の「人」＝他の女御・更衣たち",
            "「心を尽くす」の「尽くす」に「たまふ」が付くのは、他の女御が貴人だから"
          ]
        },
        {
          "type": "grammar",
          "label": "「御前渡り」の意味",
          "points": [
            "「御前渡り」＝（帝が）人の部屋の前を通ること",
            "「隙なき」＝絶え間ない — 毎日のように桐壺に通う様子",
            "「げにことわりと」＝なるほどもっともなことと（周囲の嫉妬が当然だと）"
          ]
        },
        {
          "type": "vocab",
          "label": "「心を尽くす」",
          "points": [
            "「心を尽くす」＝気を揉む・心をすり減らす",
            "現代語の「心を尽くす（全力を傾ける）」とはニュアンスが異なる",
            "「ことわり」＝道理・もっともなこと"
          ]
        }
      ]
    },
    {
      "sentenceId": "s17",
      "guide": "超長文。主語は更衣（参上する側）だが、迫害の主体（「他の女御たち」）が省略されている。敬語の違いで主語を峻別する。",
      "hints": [
        {
          "type": "subject",
          "label": "省略された迫害者",
          "points": [
            "「参う上りたまふ」＝更衣が帝のもとへ参上する（「たまふ」で更衣）",
            "「あやしきわざをしつつ」の主語は省略 → 他の女御たち（嫉妬の主体）",
            "「鎖しこめ」「はしたなめわづらはせたまふ」の主語も女御たち（最後の「たまふ」は女御が貴人だから）"
          ]
        },
        {
          "type": "structure",
          "label": "長文の三段構成",
          "points": [
            "① 打橋・渡殿で「あやしきわざ」＝汚物などを撒く嫌がらせ",
            "② 送迎の女房の裾が「まさなき」＝見苦しい状態になる",
            "③ 馬道の戸を施錠して閉じ込める — 実力行使の嫌がらせ"
          ]
        },
        {
          "type": "grammar",
          "label": "「え避らぬ」の不可能",
          "points": [
            "「え〜ぬ／ず」＝〜できない（呼応）",
            "「え避らぬ馬道」＝（通らざるを）避けられない馬道",
            "「はしたなむ」＝困らせる、「わづらふ」＝苦しめる"
          ]
        },
        {
          "type": "vocab",
          "label": "「まさなし」「はしたなむ」",
          "points": [
            "「まさなし」＝よくない・見苦しい・不都合だ",
            "「はしたなむ」＝相手にきまり悪い思いをさせる（他動詞）",
            "「うちしきる」＝たび重なる・頻繁にある"
          ]
        }
      ]
    },
    {
      "sentenceId": "s18",
      "guide": "主語転換の典型例。「思ひわびたる」は更衣、「御覧じて」以降は帝。敬語（最高敬語「御覧ず」「させたまふ」）で判別。",
      "hints": [
        {
          "type": "subject",
          "label": "主語は更衣 → 帝へ",
          "points": [
            "「思ひわびたる」の動作主は更衣（敬語なしだが文脈から）— 苦労に悩む側",
            "「御覧じて」＝「見る」の最高尊敬 → 主語は帝",
            "「移させたまひて」「賜はす」も帝（使役＋尊敬、および尊敬動詞）"
          ]
        },
        {
          "type": "grammar",
          "label": "「御覧ず」は帝専用",
          "points": [
            "「御覧ず」＝「見る」の尊敬動詞（最高敬語）",
            "原則として天皇・中宮など最高位の人物の「見る」にのみ使う",
            "この語が出たら主語はほぼ確実に帝"
          ]
        },
        {
          "type": "structure",
          "label": "「〜を〜御覧じて〜賜はす」",
          "points": [
            "「〜を」＝対象（更衣が悩むのを）",
            "「御覧じて」＝帝がご覧になって",
            "「賜はす」＝お与えになる — 他の更衣を追い出して桐壺更衣に上局を与える",
            "帝の破格の待遇が、次文の「その恨み」を生む"
          ]
        },
        {
          "type": "vocab",
          "label": "「思ひわぶ」「上局」",
          "points": [
            "「思ひわぶ」＝思い悩む・つらく思う",
            "「いといたう」＝たいそう（程度の甚だしさ）",
            "「上局」＝清涼殿近くに与えられる特別な待機所"
          ]
        }
      ]
    },
    {
      "sentenceId": "s19",
      "guide": "短い結び。主語は追い出された側の更衣。「ましてやらむ方なし」で恨みの強さを強調し、章末の余韻を残す。",
      "hints": [
        {
          "type": "subject",
          "label": "主語は追われた更衣",
          "points": [
            "「その恨み」の「その」＝前文で上局を奪われた更衣を指す",
            "主語は明示されないが、「恨み」の所有者＝追い出された更衣",
            "桐壺更衣を羨む嫉妬は宮中全体に広がる、という締めくくり"
          ]
        },
        {
          "type": "grammar",
          "label": "「やらむ方なし」",
          "points": [
            "「やる」＝晴らす・遣る（ここでは恨みを晴らす）",
            "「む」＝婉曲（〜する）",
            "「方なし」＝方法がない → 「晴らしようがない」"
          ]
        },
        {
          "type": "method",
          "label": "「まして」で章末を締める",
          "points": [
            "「まして」＝他の女御の嫉妬 → 追い出された更衣はなおさら",
            "s3の「まして」と呼応し、嫉妬の広がりを螺旋状に強調する構造",
            "短文の結びで桐壺更衣を取り巻く宮廷の険悪さを余韻として残す"
          ]
        }
      ]
    },
    {
      "sentenceId": "s20",
      "guide": "「（桐壺巻）」は巻名表示。本文の一部ではなく出典明示。",
      "hints": [
        {
          "type": "method",
          "label": "巻名表示の意味",
          "points": [
            "「桐壺巻」は『源氏物語』第一帖の題名 — 更衣の局「桐壺」に由来",
            "『源氏物語』全54帖中、ここまでで第一帖の冒頭部分",
            "次に続くのは更衣の死と光源氏の元服 — 物語の本編が始まる直前"
          ]
        }
      ]
    }
  ]
}
