{
  "textId": "a957893493",
  "questions": [
    {
      "section": "4-1. 基本テスト",
      "id": "q01",
      "question": "傍線部①とはどういう意味か。説明しなさい。",
      "answer": "〇　なんじ（２点）"
    },
    {
      "section": "4-1. 基本テスト",
      "id": "q02",
      "question": "傍線部②の本文中での意味として最も適当なものを次から選び、記号で答えなさい。\n(ア)　壊れた屋根　　(イ)　壊れた家の跡地　　(ウ)　あばら屋",
      "answer": "ウ（２点）"
    },
    {
      "section": "4-1. 基本テスト",
      "id": "q03",
      "question": "旅立ちにあたっての芭蕉の心境はどのようなものだったか。傍線部③の句を踏まえて説明しなさい。",
      "answer": "旅の途中で行き倒れ、野ざらしの身となるかも知れないが、それは自分の本望である。（４点）"
    },
    {
      "section": "4-1. 基本テスト",
      "id": "q04",
      "question": "傍線部④の句はどのような気持ちを詠んだものか。最も適当なものを次から選び、記号で答えなさい。\n(ア)　これから帰る故郷への思い。\n(イ)　旅をした十年間への思い。\n(ウ)　住み慣れた江戸を故郷とする思い。",
      "answer": "ウ（３点）"
    },
    {
      "section": "4-1. 基本テスト",
      "id": "q05",
      "question": "傍線部⑤の句の季節と季語を答えなさい。（各２点）",
      "answer": "秋・霧（２点×２）"
    },
    {
      "section": "4-1. 基本テスト",
      "id": "q06",
      "question": "傍線部⑥はどのような人物か。最も適当なものを次から選び、記号で答えなさい。\n(ア)　芭蕉の旅の道中を助ける、友人に対する信義の篤い人物。\n(イ)　芭蕉に物心を惜しみなく与えてくれる、裕福な人物。\n(ウ)　芭蕉の初めての旅を手助けしてくれた、親切な人物。",
      "answer": "ア（３点）"
    },
    {
      "section": "4-1. 基本テスト",
      "id": "q07",
      "question": "傍線部⑦の句の季節と季語を答えなさい。（各２点）",
      "answer": "秋・芭蕉（２点×２）"
    },
    {
      "section": "4-1. 基本テスト",
      "id": "q08",
      "question": "傍線部⑧とあるが、誰が堪えなかったのか。答えなさい。",
      "answer": "捨て子の親。（３点）"
    },
    {
      "section": "4-1. 基本テスト",
      "id": "q09",
      "question": "傍線部⑨に関連のある言葉として最も適当なものを次から選び、記号で答えなさい。\n(ア)　馬耳東風　　(イ)　断腸　　(ウ)　朝三暮四",
      "answer": "イ（３点）"
    },
    {
      "section": "4-1. 基本テスト",
      "id": "q01",
      "question": "〇　傍線部⑩の読みを、現代仮名遣いで記しなさい。",
      "answer": "〇　なんじ（２点）"
    },
    {
      "section": "4-1. 基本テスト",
      "id": "q01",
      "question": "次の(ア)～(ウ)の場所を芭蕉が旅をした順番に並べ替え、記号で答えなさい。（完答３点）\n(ア)　箱根の関　　(イ)　富士川のほとり　　(ウ)　江戸深川",
      "answer": "明日をも知れぬ捨て子の命と、それをどうすることもできない自分の切なさを、天命ということによって受け入れようとする気持ち。（４点）"
    },
    {
      "section": "4-2. 標準テスト",
      "id": "q01",
      "question": "傍線部①③の発句にはそれぞれ「富士」が詠み込まれているが、これらの「富士」は、作者にとってどのような存在であることが前提になっているか。簡潔に答えなさい。",
      "answer": "〇　オ・キ（２点×２。順不同）"
    },
    {
      "section": "4-2. 標準テスト",
      "id": "q02",
      "question": "傍線部②が「きわめて親しい交際」という意味になるように、空欄Ａに適当な漢字一字を補いなさい。",
      "answer": "逆（２点）"
    },
    {
      "section": "4-2. 標準テスト",
      "id": "q03",
      "question": "傍線部④と文法的働きが同じであるものを含む例文を次から選び、記号で答えなさい。\n(ア)　博士どもの書けるものも、古のは、あはれなること多かり。（徒然草）\n(イ)　今は昔、中納言なる人の、娘あまた持たまへるおはしき。（落窪物語）\n(ウ)　例の、心なしの、かかるわざをしてさいなまるるこそ、いと心づきなけれ。（源氏物語）\n(エ)　四条の大納言の、かく何ごともすぐれ、めでたくおはしますを、（大鏡）",
      "answer": "イ（２点）"
    },
    {
      "section": "4-2. 標準テスト",
      "id": "q04",
      "question": "傍線部⑤をわかりやすく現代語に訳しなさい。",
      "answer": "つらいこの世の苦しみを堪え忍ぶ（５点）"
    },
    {
      "section": "4-2. 標準テスト",
      "id": "q05",
      "question": "傍線部⑥について、次の問いに答えなさい。\n１　「露ばかりの命」とはどのような意味か、簡潔に答えなさい。\n２　「待つ間」のあとにはどのような語が省略されていると考えられるか。現代語で簡潔に答えなさい。",
      "answer": "１（露のように）はかな（く短）い命。（３点）\n２運よく拾われることもあるだろうか。（５点）"
    },
    {
      "section": "4-2. 標準テスト",
      "id": "q06",
      "question": "空欄Ｂ～Ｄに、助動詞「ん」「らん」「けん」のいずれかを、それぞれ適切な活用形に改めてあてはめなさい。（各２点）",
      "answer": "Ｂけん　Ｃらん　Ｄん（２点×３）"
    },
    {
      "section": "4-2. 標準テスト",
      "id": "q07",
      "question": "傍線部⑦は何をたとえたものか、最も適当な語を本文中から抜き出しなさい。",
      "answer": "捨て子（２点）"
    },
    {
      "section": "4-2. 標準テスト",
      "id": "q08",
      "question": "傍線部⑧の句について、次の問いに答えなさい。\n１　「猿を聞く人」とは、具体的に誰をさしているか、簡潔に答えなさい。\n２　この句が訴えていることは何か。最も適当なものを次から選び、記号で答えなさい。\n(ア)　猿の鳴き声と捨て子の泣く声を比べる人は、やはり昔から哀切こもる猿の鳴き声を悲しいと思っていること。\n(イ)　猿の鳴き声を聞きながら、さらに捨て子の泣く声を聞くと哀切きわまり、自らも泣かずにはいられなくなること。\n(ウ)　猿の鳴き声を聞く人は、泣く捨て子を目の前にしたら泣くことも笑うこともできまいと信じていること。\n(エ)　猿の鳴き声を聞く人が、猿ではなく捨て子に秋風が吹きすさぶのを目の前にしたら、この現実をどう思うのかということ。",
      "answer": "１哀しげな猿の鳴き声に涙した、かつての中国の詩人や旅人たち。（６点）\n２＝エ（４点）"
    },
    {
      "section": "4-2. 標準テスト",
      "id": "q09",
      "question": "傍線部⑨をわかりやすく現代語に訳しなさい。",
      "answer": "おまえの生まれついての身の不運を泣け（６点）"
    },
    {
      "section": "4-2. 標準テスト",
      "id": "q01",
      "question": "〇　次の作品から芭蕉と関係のないものを二つ選び、それぞれ記号で答えなさい。（各２点） \n(ア)　笈の小文　　(イ)　幻住庵記　　(ウ)　嵯峨日記　　(エ)　 猿蓑　　(オ)　新花摘　　(カ)　炭俵\n(キ)　父の終焉日記\n\n\n［解答欄省略］",
      "answer": "〇　オ・キ（２点×２。順不同）"
    },
    {
      "section": "4-3. 発展テスト",
      "id": "q01",
      "question": "傍線部①の解釈として最も適当なものを次から選び、記号で答えなさい。\n(ア)　気の向くままに旅をしたいという私の願いを狂わせる者\n(イ)　自然の中をさすらう旅に出たいという情念を狂わせる者\n(ウ)　あてもなくさすらう旅に出ることへの不安で心穏やかならざる者\n(エ)　俳諧修行の旅に出て名声を高めたいという欲望をおさえきれない者",
      "answer": "〇　第二段落では、馬に乗っていたのは作者（芭蕉）であったはずだが、第三段落では、いつの間にか荷兮の奴僕が馬に乗っている、という点。（６点）\n〈現代語訳〉\n更科の里にある姨捨山の月を見るということを、しきりに勧める秋風が、私の心の中に吹きさわいで、落ち着かなくなっていたまさにその時、私と同様に自然の中をさすらう旅に出たいという情念を狂わせる者がもう一人いて、その名を越人という。木曾谷を通る街道は、山深く道も険しく、旅寝の頼みとなる者がなくては心配だといって、荷兮さんが下男に命じて、私たちを送らせてくれた。二人は、それぞれ私にいろいろ心を向け、配慮してくれるとはいうものの、宿場や旅路のことはよく理解していない様子であって、どちらも頼りなく、物事の順序が乱れてあとさきが入れかわったりしてしまうのも、かえっておもしろく思われることが多いものだ。\n何とかいうところで、六十歳ほどの仏道に入門している僧で、おもしろそうでもおかしくありそうでもなく、ただむっつりとしている僧が、腰が押されて曲がるほどまで荷物を背負い、息を切らして、足はとぼとぼと、一歩一歩きざむように歩いて来たので、連れだってやってきた人が気の毒がって、私たちそれぞれが肩に掛けていた荷物を、例の僧が背負っていた荷物と一つに巻きつけて馬に結びつけ、私をその上に乗せた。高い山や珍しい形の峰が、頭上におおいかぶさるように重なっていて、道の左側には大河が流れ、崖の下は非常に谷が深い様子であるような思いがして、ほんのわずかな土地も平坦ではないので、鞍の上（にいる私）も落ち着いていることはできず、ただもう危ない危ないと心配する気持ちのおさまる時がない。\nあの木曾の桟橋や寝覚の床などといった歌枕を過ぎて、猿が馬場や立峠などは、四十八曲りとかいうほどに、幾重にも曲がりくねった坂道が重なり合って、自然と雲の中を通っていくような気持ちがすることだ。歩いて行く者でさえ、目がまわり、魂も縮んで、足もともおぼつかないのに、例の連れ添って（旅をして）いる（荷兮さんの）下男は、少しも怖がっている様子には見えず、馬の上でひたすら居眠りばかりしていて、落ちてしまいそうなことが何度もあったのを、後ろから見上げていると、危ないと思われること、この上もない。（だが、考えてみると）仏の御心で、われら人間どもが暮らすこの世の中をご覧になるときのお気持ちも、このようなものであろうかと、人生のはかなく頼りないことや、万物がたちまちのうちに生滅し流転してゆくことのあわただしさが、わが身のこととして自然と反省されて、（その危うさに比べると）あの阿波の鳴門は、波風もない（も同然の、穏やかなものである）ことだなあ。"
    },
    {
      "section": "4-3. 発展テスト",
      "id": "q02",
      "question": "傍線部②④の意味として最も適当なものを次から選び、それぞれ記号で答えなさい。（各２点）\n②　(ア)　心配なことだ　　　　(イ)　待ち遠しいことだ\n(ウ)　物足りないことだ　　(エ)　よくわからないことだ\n④　(ア)　いっそう　　(イ)　思いがけず\n(ウ)　かえって　　(エ)　非常に",
      "answer": "②＝ア　④＝ウ（２点×２）"
    },
    {
      "section": "4-3. 発展テスト",
      "id": "q03",
      "question": "傍線部③を現代語に訳しなさい。",
      "answer": "宿場や旅路のことはよく理解していない様子で（あって）（６点）"
    },
    {
      "section": "4-3. 発展テスト",
      "id": "q04",
      "question": "傍線部⑤について、次の問いに答えなさい。\n１　「ともなひける人」とは誰をさすと考えられるか、答えなさい。（解答は、一人とは限らない。）\n２ 　「ともなひける人」は、「あはれが」った事柄に対して具体的にどのような行動をとったか。三〇字以内で簡潔に説明しなさい。",
      "answer": "１　越人と、荷兮子が奴僕（４点）\n２　道心の僧が背負っていた多くの荷物を、馬に結びつけてあげた。［二九字］（６点）"
    },
    {
      "section": "4-3. 発展テスト",
      "id": "q05",
      "question": "傍線部⑥の現代語訳として最も適当なものを次から選び、記号で答えなさい。\n(ア)　多くの土地が平坦というわけではないので\n(イ)　少しの間も心穏やかでいることはできないので\n(ウ)　どこを通っても安心だということはないので\n(エ)　ほんのわずかな土地も平坦ではないので",
      "answer": "エ（４点）"
    },
    {
      "section": "4-3. 発展テスト",
      "id": "q06",
      "question": "傍線部⑦と文法的働きが同じであるものを含む例文を次から選び、記号で答えなさい。\n(ア)　他夫の馬より行くに…（万葉集）\n(イ)　大津より浦戸をさして漕ぎ出づ。（土佐日記）\n(ウ)　名を聞くより、やがて面影は推し量らるる心地するを、（徒然草）\n(エ)　有明の月の、板間より屋の内にさし入りたりける。（今昔物語集）",
      "answer": "ア（２点）"
    },
    {
      "section": "4-3. 発展テスト",
      "id": "q07",
      "question": "傍線部⑧の品詞分解として最も適当なものを次から選び、記号で答えなさい。\n(ア)　タ行上一段活用動詞「落つ」の連用形＋強意の助動詞「ぬ」の終止形＋当然の助動詞「べし」の連体形\n(イ)　タ行上一段活用動詞「落つ」の連用形＋完了の助動詞「ぬ」の終止形＋断定の助動詞「べし」の連体形\n(ウ)　タ行上二段活用動詞「落つ」の連用形＋強意の助動詞「ぬ」の終止形＋推量の助動詞「べし」の連体形\n(エ)　タ行上二段活用動詞「落つ」の連用形＋打消の助動詞「ず」の連体形＋反実仮想の助動詞「べし」の連体形",
      "answer": "ウ（２点）"
    },
    {
      "section": "4-3. 発展テスト",
      "id": "q08",
      "question": "傍線部⑨はどのようなことを言っているのか。最も適当なものを次から選び、記号で答えなさい。\n(ア)　いま自分は、馬から落ちずにはいるものの奴僕のことを危なっかしいと思って見ているが、仏様も自分と同じようにこの奴僕の様子を危なっかしく思い、馬から落ちないようにずっとご覧になっているのだろうということ。\n(イ)　いま自分は、馬から落ちてしまった奴僕を見て危ないことであったと思っているが、仏様もわれら人間どもの行動を危なっかしいことをするものだとご覧になっているのであろうということ。\n(ウ)　いま自分は、この後きっと馬から落ちてしまうであろう奴僕を見て危ないことだと思っているが、仏様も自分と同じようにこの奴僕の様子を危ないことだとご覧になっているのであろうということ。\n(エ)　いま自分は、何度も馬から落ちそうになっている奴僕を見て危なっかしいことだと思っているが、仏様もわれら人間どもが暮らすこの世の中を危なっかしいことだとご覧になっているのだろうということ。",
      "answer": "エ（６点）"
    },
    {
      "section": "4-3. 発展テスト",
      "id": "q09",
      "question": "傍線部⑩はどのようなことを言っているのか。最も適当なものを次から選び、記号で答えなさい。\n(ア)　人生ははかないものであるが、潮流の激しいことで有名な阿波の鳴門にも波風のない穏やかな瞬間があるように、自分の人生にも必ずや穏やかな時期が訪れるはずだということ。\n(イ)　人生がはかなく頼りないもので、あらゆる物がたちまちのうちに生滅・流転してゆくのに比べれば、潮流の激しいことで有名な阿波の鳴門は、波風がないも同然であるということ。\n(ウ)　人生は常にはかなく頼りないもので、あらゆる物がたちまちのうちに生滅・流転してゆくが、潮流の激しいことで有名な阿波の鳴門は、時にまったく波風の立たない穏やかな姿を見せるということ。\n(エ)　あらゆる物がたちまちのうちに生滅・流転してゆくのは、ちょうど阿波の鳴門にさまざまな物が吞み込まれてゆくさまに似ているが、自分はそんな世の中を波風もなく穏やかに過ごしたいものだということ。",
      "answer": "イ（６点）"
    },
    {
      "section": "4-3. 発展テスト",
      "id": "q01",
      "question": "〇　この文章の第二段落（「何々といふ所にて、～」）と第三段落（「桟はし・寝覚など過て、～」）との間で、話の展開上、明らかに不自然な点が見られるのだが、それはどのような点か。説明しなさい。\n\n\n［解答欄省略］",
      "answer": "〇　第二段落では、馬に乗っていたのは作者（芭蕉）であったはずだが、第三段落では、いつの間にか荷兮の奴僕が馬に乗っている、という点。（６点）\n〈現代語訳〉\n更科の里にある姨捨山の月を見るということを、しきりに勧める秋風が、私の心の中に吹きさわいで、落ち着かなくなっていたまさにその時、私と同様に自然の中をさすらう旅に出たいという情念を狂わせる者がもう一人いて、その名を越人という。木曾谷を通る街道は、山深く道も険しく、旅寝の頼みとなる者がなくては心配だといって、荷兮さんが下男に命じて、私たちを送らせてくれた。二人は、それぞれ私にいろいろ心を向け、配慮してくれるとはいうものの、宿場や旅路のことはよく理解していない様子であって、どちらも頼りなく、物事の順序が乱れてあとさきが入れかわったりしてしまうのも、かえっておもしろく思われることが多いものだ。\n何とかいうところで、六十歳ほどの仏道に入門している僧で、おもしろそうでもおかしくありそうでもなく、ただむっつりとしている僧が、腰が押されて曲がるほどまで荷物を背負い、息を切らして、足はとぼとぼと、一歩一歩きざむように歩いて来たので、連れだってやってきた人が気の毒がって、私たちそれぞれが肩に掛けていた荷物を、例の僧が背負っていた荷物と一つに巻きつけて馬に結びつけ、私をその上に乗せた。高い山や珍しい形の峰が、頭上におおいかぶさるように重なっていて、道の左側には大河が流れ、崖の下は非常に谷が深い様子であるような思いがして、ほんのわずかな土地も平坦ではないので、鞍の上（にいる私）も落ち着いていることはできず、ただもう危ない危ないと心配する気持ちのおさまる時がない。\nあの木曾の桟橋や寝覚の床などといった歌枕を過ぎて、猿が馬場や立峠などは、四十八曲りとかいうほどに、幾重にも曲がりくねった坂道が重なり合って、自然と雲の中を通っていくような気持ちがすることだ。歩いて行く者でさえ、目がまわり、魂も縮んで、足もともおぼつかないのに、例の連れ添って（旅をして）いる（荷兮さんの）下男は、少しも怖がっている様子には見えず、馬の上でひたすら居眠りばかりしていて、落ちてしまいそうなことが何度もあったのを、後ろから見上げていると、危ないと思われること、この上もない。（だが、考えてみると）仏の御心で、われら人間どもが暮らすこの世の中をご覧になるときのお気持ちも、このようなものであろうかと、人生のはかなく頼りないことや、万物がたちまちのうちに生滅し流転してゆくことのあわただしさが、わが身のこととして自然と反省されて、（その危うさに比べると）あの阿波の鳴門は、波風もない（も同然の、穏やかなものである）ことだなあ。"
    },
    {
      "section": "4-4. 小テストテスト",
      "id": "q01",
      "question": "漢字の読みをひらがな（現代仮名遣い）で記せ。\n①三更［　　　　　　　　］\n②甲子［　　　　　　　　］\n③江上［　　　　　　　　］\n④破屋［　　　　　　　　］",
      "answer": "①さんこう　②きのえね（かっし）　③こうしょう　④はおく（１点×４）"
    },
    {
      "section": "4-4. 小テストテスト",
      "id": "q02",
      "question": "「路粮をつつまず」とはどのようなことか。最も適当なものを次から選び、記号で答えよ。\n［　　　　］\nア　旅の安全も確認せずに\nイ　旅の食料も用意せずに\nウ　旅の餞別も受け取ることなく",
      "answer": "イ（３点）"
    },
    {
      "section": "4-4. 小テストテスト",
      "id": "q03",
      "question": "語句の意味として最も適当なものを後から選び、記号で答えよ。\n①無何［　　　　］\nア　何も存在しない空虚な世界\nイ　快楽しか存在しない平和な世界\nウ　無我無心でいられる世界\n②莫逆の交はり［　　　　］\nア　幼少の頃からの交際\nイ　たいへん親しい交際\nウ　不本意ながらの交際\n③天［　　　　］\nア　虚空\nイ　天帝\nウ　天命",
      "answer": "①ウ　②イ　③ウ（３点×３）"
    },
    {
      "section": "4-4. 小テストテスト",
      "id": "q04",
      "question": "傍線部の助動詞の文法的意味として正しいものを後から選び、記号で答えよ。\n①…と言ひけん、昔の人の杖に［　　　　］\nア　過去の伝聞\nイ　過去の原因推量\nウ　過去完了\n②かくれたり［　　　　］\nア　断定\nイ　過去\nウ　存続\n③憎むにあらじ［　　　　］\nア　打消推量\nイ　打消意志\nウ　打消当然",
      "answer": "①ア　②ウ　③ア（２点×３）"
    },
    {
      "section": "4-4. 小テストテスト",
      "id": "q05",
      "question": "「関越ゆる日は」の「越ゆる」について、以下の問いに答えよ。\n①終止形を記せ。［　　　　　　］\n②活用の行と種類を記せ。［　　　　　　　　］\n③文中での活用形を記せ。［　　　　　　］",
      "answer": "①越ゆ　②ヤ行下二段活用　③連体形（１点×３）"
    },
    {
      "section": "4-4. 小テストテスト",
      "id": "q06",
      "question": "「小萩」は何をたとえているか。最も適当なものを次から選び、記号で答えよ。\n［　　　　］\nア　芭蕉本人　　　イ　捨て子\nウ　猿を聞く人　　エ　捨て子の父母",
      "answer": "イ（３点）"
    },
    {
      "section": "4-4. 小テストテスト",
      "id": "q07",
      "question": "芭蕉と関係のない作品を二つ選び、記号で答えよ。\nア　新花摘　　イ　猿蓑　　ウ　笈の小文\nエ　父の終焉日記　　オ　幻住庵記\nカ　炭俵\n［　　　・　　　］",
      "answer": "ア・エ（１点×２）"
    }
  ]
}